README.md
setup.cfg
setup.py
camembert/__init__.py
camembert/blacklisted_ip_manager.py
camembert/content_type_setter.py
camembert/https_required.py
camembert/internal_error_manager.py
camembert/json_translator.py
camembert/logging.py
camembert/rate_limiting_manager.py
camembert/response_setter.py
camembert/server_manataince_manager.py
camembert.egg-info/PKG-INFO
camembert.egg-info/SOURCES.txt
camembert.egg-info/dependency_links.txt
camembert.egg-info/requires.txt
camembert.egg-info/top_level.txt