Metadata-Version: 2.1
Name: camembert
Version: 0.11.0
Summary: Falcon middlewares made easy.
Home-page: https://github.com/Jithinqw/Camembert
Author: Jithin Zacharia
Author-email: zachariajithin@gmail.com
License: MIT
Download-URL: https://github.com/Jithinqw/Camembert/archive/0.11.0.tar.gz
Keywords: falcon,middlewares
Platform: UNKNOWN
